topsis_code/__init__.py
topsis_code/main_code.py
102116078_topsis_py-0.2.0.dist-info/METADATA
102116078_topsis_py-0.2.0.dist-info/WHEEL
102116078_topsis_py-0.2.0.dist-info/entry_points.txt
102116078_topsis_py-0.2.0.dist-info/top_level.txt
102116078_topsis_py-0.2.0.dist-info/RECORD
