Metadata-Version: 2.1
Name: 102116078_topsis-py
Version: 0.2.0
Summary: Implementation of Topsis in Python
Author: Dhruv
Author-email: dkikan_be21@thapar.edu
Requires-Dist: numpy
Requires-Dist: pandas
